orquestra/workflow_shared/__init__.py
orquestra/workflow_shared/_git_url_utils.py
orquestra/workflow_shared/_graphs.py
orquestra/workflow_shared/_regex.py
orquestra/workflow_shared/_retry.py
orquestra/workflow_shared/abc.py
orquestra/workflow_shared/dispatch.py
orquestra/workflow_shared/env.py
orquestra/workflow_shared/exceptions.py
orquestra/workflow_shared/py.typed
orquestra/workflow_shared/serde.py
orquestra/workflow_shared/_spaces/__init__.py
orquestra/workflow_shared/_spaces/_structs.py
orquestra/workflow_shared/dates/__init__.py
orquestra/workflow_shared/dates/_dates.py
orquestra/workflow_shared/exec_ctx/__init__.py
orquestra/workflow_shared/exec_ctx/_exec_ctx.py
orquestra/workflow_shared/kubernetes/__init__.py
orquestra/workflow_shared/kubernetes/quantity.py
orquestra/workflow_shared/logs/__init__.py
orquestra/workflow_shared/logs/_interfaces.py
orquestra/workflow_shared/logs/_models.py
orquestra/workflow_shared/logs/_regrouping.py
orquestra/workflow_shared/orqdantic/__init__.py
orquestra/workflow_shared/orqdantic/orqdantic.py
orquestra/workflow_shared/packaging/__init__.py
orquestra/workflow_shared/packaging/_versions.py
orquestra/workflow_shared/schema/__init__.py
orquestra/workflow_shared/schema/_compat.py
orquestra/workflow_shared/schema/configs.py
orquestra/workflow_shared/schema/ir.py
orquestra/workflow_shared/schema/responses.py
orquestra/workflow_shared/schema/workflow_run.py
orquestra/workflow_shared/secrets/__init__.py
orquestra/workflow_shared/secrets/_api.py
orquestra/workflow_shared/secrets/_auth.py
orquestra/workflow_shared/secrets/_client.py
orquestra/workflow_shared/secrets/_exceptions.py
orquestra/workflow_shared/secrets/_models.py
orquestra_workflow_shared-2.0.0.dist-info/METADATA
orquestra_workflow_shared-2.0.0.dist-info/WHEEL
orquestra_workflow_shared-2.0.0.dist-info/licenses/LICENSE
orquestra_workflow_shared-2.0.0.dist-info/RECORD
