Metadata-Version: 2.3
Name: orquestra-workflow-shared
Version: 2.0.0
Summary: Code shared between Orquestra SDK clients and workflow execution servers
Project-URL: Homepage, https://github.com/zapata-engineering/orquestra-sdk
Project-URL: Documentation, https://docs.orquestra.io
Project-URL: Repository, https://github.com/zapata-engineering/orquestra-sdk.git
Project-URL: Issues, https://github.com/zapata-engineering/orquestra-sdk/issues
Author-email: "Zapata Computing Inc." <info@zapatacomputing.com>
License:                                  Apache License
License-File: LICENSE
Classifier: License :: OSI Approved :: Apache Software License
Classifier: Operating System :: OS Independent
Classifier: Programming Language :: Python :: 3
Classifier: Topic :: Scientific/Engineering
Requires-Python: >=3.8
Requires-Dist: cloudpickle==2.2.1
Requires-Dist: packaging>=21
Requires-Dist: pydantic>1.10.7
Requires-Dist: requests>=2.28
Requires-Dist: typing-extensions>=4.1.0
Requires-Dist: urllib3
Provides-Extra: dev
Requires-Dist: black~=23.7; extra == 'dev'
Requires-Dist: diff-cover; extra == 'dev'
Requires-Dist: flake8-pyproject>=1.2.3; extra == 'dev'
Requires-Dist: flake8>=4.0.0; extra == 'dev'
Requires-Dist: freezegun; extra == 'dev'
Requires-Dist: isort~=5.9.0; extra == 'dev'
Requires-Dist: mypy~=0.910; extra == 'dev'
Requires-Dist: numpy; extra == 'dev'
Requires-Dist: pydoclint; extra == 'dev'
Requires-Dist: pymarkdownlnt; extra == 'dev'
Requires-Dist: pyright; extra == 'dev'
Requires-Dist: pytest-cov>=2.12; extra == 'dev'
Requires-Dist: pytest>=6.2; extra == 'dev'
Requires-Dist: ruff>=0.2.0; extra == 'dev'
Requires-Dist: types-requests; extra == 'dev'
